README.md
requirements.txt
setup.cfg
setup.py
mms_stacky.egg-info/PKG-INFO
mms_stacky.egg-info/SOURCES.txt
mms_stacky.egg-info/dependency_links.txt
mms_stacky.egg-info/entry_points.txt
mms_stacky.egg-info/requires.txt
mms_stacky.egg-info/top_level.txt
stacky/__init__.py
stacky/app.py
stacky/commands.py
stacky/config.py
stacky/dependency.py
stacky/iter.py
tests/__init__.py
tests/test_app.py
tests/test_commands.py
tests/test_config.py
tests/test_dependency.py