Metadata-Version: 2.1
Name: mms-stacky
Version: 0.0.5
Summary: A service management tool for local development.
Home-page: https://gitlab.com/mega-mac-slice/stacky
Author: mega-mac-slice
Author-email: megamacslice@protonmail.com
License: MIT
Platform: UNKNOWN
Provides-Extra: dev
